NCPNet/__init__.py
NCPNet/__main__.py
NCPNet/brain_data.py
NCPNet/loader.py
NCPNet/predict.py
NCPNet/task.py
NCPNet/trainer.py
NCPNet/utils.py
NCPNet/approaches/Decoder.py
NCPNet/approaches/Encoder.py
NCPNet/approaches/PairEncoder.py
NCPNet/approaches/__init__.py
NCPNet/approaches/method.py
NCPNet-1.0.4.dist-info/LICENSE
NCPNet-1.0.4.dist-info/METADATA
NCPNet-1.0.4.dist-info/WHEEL
NCPNet-1.0.4.dist-info/top_level.txt
NCPNet-1.0.4.dist-info/RECORD
