Metadata-Version: 2.1
Name: NCPNet
Version: 1.0.4
Summary: Learning synapse-level brain circuit networks. Include training, inferring, evaluation, and visualization.
Home-page: https://github.com/mxz12119/NCPNet
Author: Guojia Wan
Author-email: guojiawan@whu.edu.cn
Classifier: Programming Language :: Python :: 3
Classifier: License :: OSI Approved :: MIT License
Classifier: Operating System :: OS Independent
Requires-Python: >=3.7
License-File: LICENSE
Requires-Dist: torch-geometric (>=2.3.1)
Requires-Dist: torch-cluster (>=1.6.1)
Requires-Dist: torch-sparse (>=0.6.17)
Requires-Dist: torch-scatter (>=2.1.1)
Requires-Dist: navis (==1.4.0)
Requires-Dist: neuprint-python (==0.4.25)
Requires-Dist: networkx
Requires-Dist: tqdm
Requires-Dist: tensorboardx
Requires-Dist: pandas
Requires-Dist: numpy
Requires-Dist: scikit-learn
Requires-Dist: zmq
Requires-Dist: pyyaml
